installer_creator/__init__.py
installer_creator/__main__.py
installer_creator/build_exe.py
installer_creator/build_installer.py
installer_creator/changelog_generator.py
installer_creator/cli.py
installer_creator/config_editor.py
installer_creator/config_editor.ui
installer_creator/config_editor_ui.py
installer_creator/favicon.ico
installer_creator/installer_creator_logo.png
installer_creator/installer_creator_logo.svg
installer_creator/uuid_generator.py
installer_creator-0.2.3.dist-info/licenses/LICENSE
installer_creator-0.2.3.dist-info/METADATA
installer_creator-0.2.3.dist-info/WHEEL
installer_creator-0.2.3.dist-info/entry_points.txt
installer_creator-0.2.3.dist-info/top_level.txt
installer_creator-0.2.3.dist-info/RECORD
