Metadata-Version: 2.4
Name: installer_creator
Version: 0.2.3
Summary: Python package for compiling projects with Nuitka and creating Windows installers with Wix Toolset
License-Expression: LGPL-3.0-or-later
Project-URL: homepage, https://github.com/steveway/installer_creator
Project-URL: issues, https://github.com/steveway/installer_creator/issues
Classifier: Development Status :: 4 - Beta
Classifier: Intended Audience :: Developers
Classifier: Programming Language :: Python :: 3
Classifier: Programming Language :: Python :: 3.7
Classifier: Programming Language :: Python :: 3.8
Classifier: Programming Language :: Python :: 3.9
Classifier: Programming Language :: Python :: 3.10
Classifier: Programming Language :: Python :: 3.11
Classifier: Programming Language :: Python :: 3.12
Classifier: Topic :: Software Development :: Build Tools
Classifier: Topic :: Software Development :: Libraries :: Python Modules
Classifier: Topic :: Utilities
Requires-Python: >=3.7
License-File: LICENSE
Requires-Dist: nuitka
Requires-Dist: pyyaml
Requires-Dist: psutil
Requires-Dist: rich
Requires-Dist: pywinpty; platform_system == "Windows"
Dynamic: license-file
